crashless/__init__.py
crashless/cts.py
crashless/django_handler.py
crashless/fastapi_handler.py
crashless/handler.py
crashless-0.0.20.dist-info/LICENSE
crashless-0.0.20.dist-info/METADATA
crashless-0.0.20.dist-info/WHEEL
crashless-0.0.20.dist-info/top_level.txt
crashless-0.0.20.dist-info/RECORD
