Metadata-Version: 2.1
Name: crashless
Version: 0.0.20
Summary: Bugless future for our sanity sake
Author-email: Juan Isaza <biosolardecolombia@gmail.com>
Project-URL: Homepage, https://github.com/jisazaTappsi/crashless
Project-URL: Issues, https://github.com/jisazaTappsi/crashless/issues
Classifier: Programming Language :: Python :: 3
Classifier: License :: OSI Approved :: MIT License
Classifier: Operating System :: OS Independent
Requires-Python: >=3.8
License-File: LICENSE
Requires-Dist: fastapi >=0.83.0
Requires-Dist: pydantic >=1.10.19
Requires-Dist: requests >=2.0.0
Requires-Dist: halo >=0.0.31
